argformat/__init__.py
argformat/formatter.py
argformat-0.0.3.dist-info/LICENSE
argformat-0.0.3.dist-info/METADATA
argformat-0.0.3.dist-info/WHEEL
argformat-0.0.3.dist-info/top_level.txt
argformat-0.0.3.dist-info/RECORD
