Metadata-Version: 2.1
Name: argformat
Version: 0.0.3
Summary: Provides a structured formatter for the argparse module
Home-page: https://github.com/Thijsvanede/argformat
Author: Thijs van Ede
Author-email: t.s.vanede@utwente.nl
License: UNKNOWN
Platform: UNKNOWN
Classifier: Programming Language :: Python :: 3
Classifier: License :: OSI Approved :: MIT License
Classifier: Operating System :: OS Independent
